fnny
