Metadata-Version: 1.1
Name: fnny
Version: 0.0.2
Summary: Hot function generators
Home-page: https://github.com/cpdean/fnny
Author: Conrad Dean
Author-email: conrad.p.dean@gmail.com
License: MIT
Keywords: functional programming higher-ordered
Platform: UNKNOWN
Classifier: Development Status :: 3 - Alpha
Classifier: Environment :: Console
Classifier: Intended Audience :: Developers
Classifier: Programming Language :: Python
Classifier: Programming Language :: Python :: 3
Classifier: Programming Language :: Python :: Implementation :: CPython
